<annotation>
	<folder>od_dogs</folder>
	<filename>murilo-viviani-G9eHjFC_230-unsplash.jpg</filename>
	<path>C:\Users\nakata\Python\myfolder\od_test\od_dogs\murilo-viviani-G9eHjFC_230-unsplash.jpg</path>
	<source>
		<database>Unknown</database>
	</source>
	<size>
		<width>640</width>
		<height>427</height>
		<depth>3</depth>
	</size>
	<segmented>0</segmented>
	<object>
		<name>dog</name>
		<pose>Unspecified</pose>
		<truncated>0</truncated>
		<difficult>0</difficult>
		<bndbox>
			<xmin>242</xmin>
			<ymin>174</ymin>
			<xmax>583</xmax>
			<ymax>362</ymax>
		</bndbox>
	</object>
</annotation>
